tcbs/__init__.py
tcbs/auth.py
tcbs/client.py
tcbs/exceptions.py
tcbs-0.1.0.dist-info/licenses/LICENSE
tcbs-0.1.0.dist-info/METADATA
tcbs-0.1.0.dist-info/WHEEL
tcbs-0.1.0.dist-info/top_level.txt
tcbs-0.1.0.dist-info/RECORD
