Metadata-Version: 2.4
Name: tcbs
Version: 0.1.0
Summary: Lightweight Python SDK for Techcom Securities (TCBS) iFlash Open API
Home-page: https://github.com/tcbs/tcbs-python-sdk
Author: TCBS SDK Contributors
Author-email: TCBS SDK Contributors <cskh@tcbs.com.vn>
License: MIT
Project-URL: Homepage, https://developers.tcbs.com.vn
Project-URL: Documentation, https://developers.tcbs.com.vn
Project-URL: Repository, https://github.com/tcbs/tcbs-python-sdk
Project-URL: Bug Reports, https://github.com/tcbs/tcbs-python-sdk/issues
Keywords: tcbs,techcom,securities,trading,stocks,derivatives,vietnam,api,iflash
Classifier: Development Status :: 3 - Alpha
Classifier: Intended Audience :: Developers
Classifier: Intended Audience :: Financial and Insurance Industry
Classifier: Topic :: Office/Business :: Financial :: Investment
Classifier: License :: OSI Approved :: MIT License
Classifier: Programming Language :: Python :: 3
Classifier: Programming Language :: Python :: 3.8
Classifier: Programming Language :: Python :: 3.9
Classifier: Programming Language :: Python :: 3.10
Classifier: Programming Language :: Python :: 3.11
Classifier: Programming Language :: Python :: 3.12
Classifier: Operating System :: OS Independent
Requires-Python: >=3.8
License-File: LICENSE
Requires-Dist: requests>=2.25.0
Provides-Extra: dev
Requires-Dist: pytest>=7.0.0; extra == "dev"
Requires-Dist: pytest-cov>=4.0.0; extra == "dev"
Requires-Dist: black>=22.0.0; extra == "dev"
Requires-Dist: flake8>=5.0.0; extra == "dev"
Requires-Dist: mypy>=0.990; extra == "dev"
Dynamic: author
Dynamic: home-page
Dynamic: license-file
Dynamic: requires-python
